{"is_source_file": true, "format": "Python", "description": "This file defines the URL routing for a Django application, specifically a route for a health check endpoint.", "external_files": ["views.py"], "external_methods": ["views.health"], "published": ["urlpatterns"], "classes": [], "methods": [], "calls": ["django.urls.path"], "search-terms": ["Django", "urls", "health"], "state": 2, "file_id": 3, "knowledge_revision": 26, "git_revision": "04bbc8cd29c219dff1c6b958c4cb9080fcbe4fe9", "ctags": [{"_type": "tag", "name": "urlpatterns", "path": "/tmp/kavia/workspace/code-generation/hello-world-application-4323-4333/backend_django/api/urls.py", "pattern": "/^urlpatterns = [$/", "language": "Python", "kind": "variable"}], "hash": "b0c92d4c1f622aa361c1fb5a0594d5d6", "format-version": 4, "code-base-name": "backend_django", "filename": "backend_django/api/urls.py", "fields": [{"name": "urlpatterns = [", "scope": "", "scopeKind": "", "description": "unavailable"}], "revision_history": [{"26": "04bbc8cd29c219dff1c6b958c4cb9080fcbe4fe9"}]}